pysplashsph-0.0.2.post1.dist-info/WHEEL
pysplashsph-0.0.2.post1.dist-info/RECORD
pysplashsph-0.0.2.post1.dist-info/LICENSE
pysplashsph-0.0.2.post1.dist-info/top_level.txt
pysplashsph-0.0.2.post1.dist-info/METADATA
pysplashsph/__init__.py
pysplashsph/exact/__init__.py
pysplashsph/exact/exact.py
pysplashsph/interpolation/__init__.py
pysplashsph/interpolation/interpolation.py
pysplashsph/libs/libgfortran-ed201abd.so.3.0.0
pysplashsph/libs/libgomp-3300acd3.so.1.0.0
pysplashsph/libs/libread.so
pysplashsph/libs/libexact.so
pysplashsph/utils/utils.py
pysplashsph/utils/__init__.py
pysplashsph/read/__init__.py
pysplashsph/read/read.py
