Metadata-Version: 2.1
Name: pysplashsph
Version: 0.0.2.post1
Summary: Python wrapper module around SPLASH utilities.
Home-page: https://github.com/joshcalcino/pysplashsph
Author: Josh Calcino
Author-email: josh.calcino@gmail.com
License: MIT
Platform: UNKNOWN
Classifier: Development Status :: 2 - Pre-Alpha
Classifier: License :: OSI Approved :: MIT License
Classifier: Programming Language :: Python :: 3.6
Classifier: Programming Language :: Python :: 3.7
Classifier: Programming Language :: Python :: 3.8
Classifier: Operating System :: POSIX :: Linux
Classifier: Operating System :: MacOS
Classifier: Topic :: Scientific/Engineering :: Astronomy
Classifier: Topic :: Scientific/Engineering :: Visualization
Requires-Dist: setuptools (>=46.0.0)
Requires-Dist: numpy (>=1.18.1)
Requires-Dist: h5py (>=2.10.0)
Requires-Dist: pandas (>=1.0.1)
